wumpy/models/__init__.py
wumpy/models/_asset.py
wumpy/models/_base.py
wumpy/models/_channels.py
wumpy/models/_components.py
wumpy/models/_embed.py
wumpy/models/_emoji.py
wumpy/models/_flags.py
wumpy/models/_guild.py
wumpy/models/_integrations.py
wumpy/models/_interactions.py
wumpy/models/_invite.py
wumpy/models/_member.py
wumpy/models/_message.py
wumpy/models/_permissions.py
wumpy/models/_role.py
wumpy/models/_sticker.py
wumpy/models/_user.py
wumpy/models/_utils.py
wumpy/models/py.typed
wumpy_models-0.1.0.dist-info/WHEEL
wumpy_models-0.1.0.dist-info/METADATA
wumpy_models-0.1.0.dist-info/RECORD
